{
  "date": "2026-02-16",
  "bets": [
    {
      "game": "Miss Valley St Delta Devils @ Alabama St Hornets",
      "sport": "\ud83c\udfc0 NCAA Basketball",
      "bet_type": "SPREAD",
      "recommendation": "Alabama St Hornets -16.5",
      "fanduel_line": "Alabama St Hornets -16.5 / Miss Valley St Delta Devils 16.5",
      "edge": 6.6,
      "confidence": 82,
      "risk_tier": "\ud83d\udfe2 LOW RISK",
      "game_time": "07:00 PM EST",
      "reason": "\u2022 Model favors Alabama by ~23 points\n\u2022 Strong cover opportunity with 82% confidence\n\u2022 6.6 point edge identified\u2014market inefficiency",
      "model_version": "REAL v1.0 (Live OddsAPI)",
      "data_source": "OddsAPI",
      "bet_instructions": "\ud83d\udccd PLACE BET ON FanDuel: Alabama St Hornets -16.5 (SPREAD) | Bet on Alabama St Hornets to win by 17+ points | Confidence: 82%",
      "bet_explanation": "Bet on Alabama St Hornets to win by 17+ points",
      "bookmaker_source": "FanDuel",
      "smart_edge": -0.1,
      "smart_edge_quality": "Marginal",
      "smart_edge_confidence": 55,
      "smart_edge_reasoning": "Edge Assessment: Marginal (0.0pt from team strength)",
      "edge_components": {
        "team_strength_edge": 0.0,
        "injury_edge": 0,
        "weather_edge": 0,
        "historical_edge": -0.09899999999999992,
        "variance_adjustment": 0
      },
      "result": "WIN",
      "final_score": "55-92",
      "away_score": 55,
      "home_score": 92
    },
    {
      "game": "Howard Bison @ Delaware St Hornets",
      "sport": "\ud83c\udfc0 NCAA Basketball",
      "bet_type": "SPREAD",
      "recommendation": "Howard Bison -12.5",
      "fanduel_line": "Delaware St Hornets 12.5 / Howard Bison -12.5",
      "edge": 5.0,
      "confidence": 82,
      "risk_tier": "\ud83d\udfe2 LOW RISK",
      "game_time": "07:00 PM EST",
      "reason": "\u2022 Model favors Howard by ~17 points\n\u2022 Strong cover opportunity with 82% confidence\n\u2022 5.0 point edge identified\u2014market inefficiency",
      "model_version": "REAL v1.0 (Live OddsAPI)",
      "data_source": "OddsAPI",
      "bet_instructions": "\ud83d\udccd PLACE BET ON FanDuel: Howard Bison -12.5 (SPREAD) | Bet on Howard Bison to win straight up or lose by less than 12 points | Confidence: 82%",
      "bet_explanation": "Bet on Howard Bison to win straight up or lose by less than 12 points",
      "bookmaker_source": "FanDuel",
      "smart_edge": -0.1,
      "smart_edge_quality": "Marginal",
      "smart_edge_confidence": 55,
      "smart_edge_reasoning": "Edge Assessment: Marginal (0.0pt from team strength)",
      "edge_components": {
        "team_strength_edge": 0.0,
        "injury_edge": 0,
        "weather_edge": 0,
        "historical_edge": -0.09899999999999992,
        "variance_adjustment": 0
      },
      "result": "WIN",
      "final_score": "91-59",
      "away_score": 91,
      "home_score": 59
    },
    {
      "game": "McNeese Cowboys @ Northwestern St Demons",
      "sport": "\ud83c\udfc0 NCAA Basketball",
      "bet_type": "SPREAD",
      "recommendation": "McNeese Cowboys -14.5",
      "fanduel_line": "Northwestern St Demons 14.5 / McNeese Cowboys -14.5",
      "edge": 5.8,
      "confidence": 82,
      "risk_tier": "\ud83d\udfe2 LOW RISK",
      "game_time": "07:30 PM EST",
      "reason": "\u2022 Model favors McNeese by ~20 points\n\u2022 Strong cover opportunity with 82% confidence\n\u2022 5.8 point edge identified\u2014market inefficiency",
      "model_version": "REAL v1.0 (Live OddsAPI)",
      "data_source": "OddsAPI",
      "bet_instructions": "\ud83d\udccd PLACE BET ON FanDuel: McNeese Cowboys -14.5 (SPREAD) | Bet on McNeese Cowboys to win straight up or lose by less than 14 points | Confidence: 82%",
      "bet_explanation": "Bet on McNeese Cowboys to win straight up or lose by less than 14 points",
      "bookmaker_source": "FanDuel",
      "smart_edge": -0.1,
      "smart_edge_quality": "Marginal",
      "smart_edge_confidence": 55,
      "smart_edge_reasoning": "Edge Assessment: Marginal (0.0pt from team strength)",
      "edge_components": {
        "team_strength_edge": 0.0,
        "injury_edge": 0,
        "weather_edge": 0,
        "historical_edge": -0.09899999999999992,
        "variance_adjustment": 0
      },
      "result": "LOSS",
      "final_score": "75-64",
      "away_score": 75,
      "home_score": 64
    },
    {
      "game": "Wagner Seahawks @ LIU Sharks",
      "sport": "\ud83c\udfc0 NCAA Basketball",
      "bet_type": "SPREAD",
      "recommendation": "LIU Sharks -10.5",
      "fanduel_line": "LIU Sharks -10.5 / Wagner Seahawks 10.5",
      "edge": 4.2,
      "confidence": 80,
      "risk_tier": "\ud83d\udfe2 LOW RISK",
      "game_time": "07:00 PM EST",
      "reason": "\u2022 Model favors LIU by ~14 points\n\u2022 Strong cover opportunity with 80% confidence\n\u2022 4.2 point edge identified\u2014market inefficiency",
      "model_version": "REAL v1.0 (Live OddsAPI)",
      "data_source": "OddsAPI",
      "bet_instructions": "\ud83d\udccd PLACE BET ON FanDuel: LIU Sharks -10.5 (SPREAD) | Bet on LIU Sharks to win by 11+ points | Confidence: 80%",
      "bet_explanation": "Bet on LIU Sharks to win by 11+ points",
      "bookmaker_source": "FanDuel",
      "smart_edge": -0.1,
      "smart_edge_quality": "Marginal",
      "smart_edge_confidence": 55,
      "smart_edge_reasoning": "Edge Assessment: Marginal (0.0pt from team strength)",
      "edge_components": {
        "team_strength_edge": 0.0,
        "injury_edge": 0,
        "weather_edge": 0,
        "historical_edge": -0.09899999999999992,
        "variance_adjustment": 0
      },
      "result": "WIN",
      "final_score": "65-83",
      "away_score": 65,
      "home_score": 83
    },
    {
      "game": "Lamar Cardinals @ UT Rio Grande Valley Vaqueros",
      "sport": "\ud83c\udfc0 NCAA Basketball",
      "bet_type": "SPREAD",
      "recommendation": "UT Rio Grande Valley Vaqueros -6.5",
      "fanduel_line": "UT Rio Grande Valley Vaqueros -6.5 / Lamar Cardinals 6.5",
      "edge": 2.6,
      "confidence": 74,
      "risk_tier": "\ud83d\udfe2 LOW RISK",
      "game_time": "07:30 PM EST",
      "reason": "\u2022 Model favors UT by ~9 points\n\u2022 Strong cover opportunity with 74% confidence\n\u2022 2.6 point edge identified\u2014market inefficiency",
      "model_version": "REAL v1.0 (Live OddsAPI)",
      "data_source": "OddsAPI",
      "bet_instructions": "\ud83d\udccd PLACE BET ON FanDuel: UT Rio Grande Valley Vaqueros -6.5 (SPREAD) | Bet on UT Rio Grande Valley Vaqueros to win by 7+ points | Confidence: 74%",
      "bet_explanation": "Bet on UT Rio Grande Valley Vaqueros to win by 7+ points",
      "bookmaker_source": "FanDuel",
      "smart_edge": -0.1,
      "smart_edge_quality": "Marginal",
      "smart_edge_confidence": 55,
      "smart_edge_reasoning": "Edge Assessment: Marginal (0.0pt from team strength)",
      "edge_components": {
        "team_strength_edge": 0.0,
        "injury_edge": 0,
        "weather_edge": 0,
        "historical_edge": -0.09899999999999992,
        "variance_adjustment": 0
      },
      "result": "LOSS",
      "final_score": "65-70",
      "away_score": 65,
      "home_score": 70
    },
    {
      "game": "Coppin St Eagles @ South Carolina St Bulldogs",
      "sport": "\ud83c\udfc0 NCAA Basketball",
      "bet_type": "SPREAD",
      "recommendation": "South Carolina St Bulldogs -5.5",
      "fanduel_line": "South Carolina St Bulldogs -5.5 / Coppin St Eagles 5.5",
      "edge": 2.2,
      "confidence": 73,
      "risk_tier": "\ud83d\udfe2 LOW RISK",
      "game_time": "04:30 PM EST",
      "reason": "\u2022 Model favors South by ~7 points\n\u2022 Strong cover opportunity with 73% confidence\n\u2022 2.2 point edge identified\u2014market inefficiency",
      "model_version": "REAL v1.0 (Live OddsAPI)",
      "data_source": "OddsAPI",
      "bet_instructions": "\ud83d\udccd PLACE BET ON FanDuel: South Carolina St Bulldogs -5.5 (SPREAD) | Bet on South Carolina St Bulldogs to win by 6+ points | Confidence: 73%",
      "bet_explanation": "Bet on South Carolina St Bulldogs to win by 6+ points",
      "bookmaker_source": "FanDuel",
      "smart_edge": -0.1,
      "smart_edge_quality": "Marginal",
      "smart_edge_confidence": 55,
      "smart_edge_reasoning": "Edge Assessment: Marginal (0.0pt from team strength)",
      "edge_components": {
        "team_strength_edge": 0.0,
        "injury_edge": 0,
        "weather_edge": 0,
        "historical_edge": -0.09899999999999992,
        "variance_adjustment": 0
      },
      "result": "LOSS",
      "final_score": "59-57",
      "away_score": 59,
      "home_score": 57
    },
    {
      "game": "Louisiana Ragin' Cajuns @ Old Dominion Monarchs",
      "sport": "\ud83c\udfc0 NCAA Basketball",
      "bet_type": "SPREAD",
      "recommendation": "Old Dominion Monarchs -5.5",
      "fanduel_line": "Old Dominion Monarchs -5.5 / Louisiana Ragin' Cajuns 5.5",
      "edge": 2.2,
      "confidence": 73,
      "risk_tier": "\ud83d\udfe2 LOW RISK",
      "game_time": "05:00 PM EST",
      "reason": "\u2022 Model favors Old by ~7 points\n\u2022 Strong cover opportunity with 73% confidence\n\u2022 2.2 point edge identified\u2014market inefficiency",
      "model_version": "REAL v1.0 (Live OddsAPI)",
      "data_source": "OddsAPI",
      "bet_instructions": "\ud83d\udccd PLACE BET ON FanDuel: Old Dominion Monarchs -5.5 (SPREAD) | Bet on Old Dominion Monarchs to win by 6+ points | Confidence: 73%",
      "bet_explanation": "Bet on Old Dominion Monarchs to win by 6+ points",
      "bookmaker_source": "FanDuel",
      "smart_edge": -0.1,
      "smart_edge_quality": "Marginal",
      "smart_edge_confidence": 55,
      "smart_edge_reasoning": "Edge Assessment: Marginal (0.0pt from team strength)",
      "edge_components": {
        "team_strength_edge": 0.0,
        "injury_edge": 0,
        "weather_edge": 0,
        "historical_edge": -0.09899999999999992,
        "variance_adjustment": 0
      },
      "result": "WIN",
      "final_score": "72-83",
      "away_score": 72,
      "home_score": 83
    },
    {
      "game": "Stephen F. Austin Lumberjacks @ Texas A&M-CC Islanders",
      "sport": "\ud83c\udfc0 NCAA Basketball",
      "bet_type": "SPREAD",
      "recommendation": "Stephen F. Austin Lumberjacks -5.5",
      "fanduel_line": "Texas A&M-CC Islanders 5.5 / Stephen F. Austin Lumberjacks -5.5",
      "edge": 2.2,
      "confidence": 73,
      "risk_tier": "\ud83d\udfe2 LOW RISK",
      "game_time": "08:00 PM EST",
      "reason": "\u2022 Model favors Stephen by ~7 points\n\u2022 Strong cover opportunity with 73% confidence\n\u2022 2.2 point edge identified\u2014market inefficiency",
      "model_version": "REAL v1.0 (Live OddsAPI)",
      "data_source": "OddsAPI",
      "bet_instructions": "\ud83d\udccd PLACE BET ON FanDuel: Stephen F. Austin Lumberjacks -5.5 (SPREAD) | Bet on Stephen F. Austin Lumberjacks to win straight up or lose by less than 5 points | Confidence: 73%",
      "bet_explanation": "Bet on Stephen F. Austin Lumberjacks to win straight up or lose by less than 5 points",
      "bookmaker_source": "FanDuel",
      "smart_edge": -0.1,
      "smart_edge_quality": "Marginal",
      "smart_edge_confidence": 55,
      "smart_edge_reasoning": "Edge Assessment: Marginal (0.0pt from team strength)",
      "edge_components": {
        "team_strength_edge": 0.0,
        "injury_edge": 0,
        "weather_edge": 0,
        "historical_edge": -0.09899999999999992,
        "variance_adjustment": 0
      },
      "result": "WIN",
      "final_score": "78-68",
      "away_score": 78,
      "home_score": 68
    },
    {
      "game": "Bethune-Cookman Wildcats @ Jackson St Tigers",
      "sport": "\ud83c\udfc0 NCAA Basketball",
      "bet_type": "SPREAD",
      "recommendation": "Bethune-Cookman Wildcats -4.5",
      "fanduel_line": "Jackson St Tigers 4.5 / Bethune-Cookman Wildcats -4.5",
      "edge": 1.8,
      "confidence": 71,
      "risk_tier": "\ud83d\udfe1 MODERATE RISK",
      "game_time": "07:00 PM EST",
      "reason": "\u2022 Model favors Bethune-Cookman by ~6 points\n\u2022 Strong cover opportunity with 71% confidence",
      "model_version": "REAL v1.0 (Live OddsAPI)",
      "data_source": "OddsAPI",
      "bet_instructions": "\ud83d\udccd PLACE BET ON FanDuel: Bethune-Cookman Wildcats -4.5 (SPREAD) | Bet on Bethune-Cookman Wildcats to win straight up or lose by less than 4 points | Confidence: 71%",
      "bet_explanation": "Bet on Bethune-Cookman Wildcats to win straight up or lose by less than 4 points",
      "bookmaker_source": "FanDuel",
      "smart_edge": -0.1,
      "smart_edge_quality": "Marginal",
      "smart_edge_confidence": 55,
      "smart_edge_reasoning": "Edge Assessment: Marginal (0.0pt from team strength)",
      "edge_components": {
        "team_strength_edge": 0.0,
        "injury_edge": 0,
        "weather_edge": 0,
        "historical_edge": -0.09899999999999992,
        "variance_adjustment": 0
      },
      "result": "WIN",
      "final_score": "86-91",
      "away_score": 86,
      "home_score": 91
    },
    {
      "game": "South Alabama Jaguars @ Marshall Thundering Herd",
      "sport": "\ud83c\udfc0 NCAA Basketball",
      "bet_type": "SPREAD",
      "recommendation": "Marshall Thundering Herd -3.5",
      "fanduel_line": "Marshall Thundering Herd -3.5 / South Alabama Jaguars 3.5",
      "edge": 1.4,
      "confidence": 70,
      "risk_tier": "\ud83d\udfe1 MODERATE RISK",
      "game_time": "07:00 PM EST",
      "reason": "\u2022 Model favors Marshall by ~4 points\n\u2022 Strong cover opportunity with 70% confidence",
      "model_version": "REAL v1.0 (Live OddsAPI)",
      "data_source": "OddsAPI",
      "bet_instructions": "\ud83d\udccd PLACE BET ON FanDuel: Marshall Thundering Herd -3.5 (SPREAD) | Bet on Marshall Thundering Herd to win by 4+ points | Confidence: 70%",
      "bet_explanation": "Bet on Marshall Thundering Herd to win by 4+ points",
      "bookmaker_source": "FanDuel",
      "smart_edge": -0.1,
      "smart_edge_quality": "Marginal",
      "smart_edge_confidence": 55,
      "smart_edge_reasoning": "Edge Assessment: Marginal (0.0pt from team strength)",
      "edge_components": {
        "team_strength_edge": 0.0,
        "injury_edge": 0,
        "weather_edge": 0,
        "historical_edge": -0.09899999999999992,
        "variance_adjustment": 0
      },
      "result": "WIN",
      "final_score": "80-84",
      "away_score": 80,
      "home_score": 84
    },
    {
      "game": "Morgan St Bears @ North Carolina Central Eagles",
      "sport": "\ud83c\udfc0 NCAA Basketball",
      "bet_type": "SPREAD",
      "recommendation": "North Carolina Central Eagles -3.5",
      "fanduel_line": "North Carolina Central Eagles -3.5 / Morgan St Bears 3.5",
      "edge": 1.4,
      "confidence": 70,
      "risk_tier": "\ud83d\udfe1 MODERATE RISK",
      "game_time": "07:00 PM EST",
      "reason": "\u2022 Model favors North by ~4 points\n\u2022 Strong cover opportunity with 70% confidence",
      "model_version": "REAL v1.0 (Live OddsAPI)",
      "data_source": "OddsAPI",
      "bet_instructions": "\ud83d\udccd PLACE BET ON FanDuel: North Carolina Central Eagles -3.5 (SPREAD) | Bet on North Carolina Central Eagles to win by 4+ points | Confidence: 70%",
      "bet_explanation": "Bet on North Carolina Central Eagles to win by 4+ points",
      "bookmaker_source": "FanDuel",
      "smart_edge": -0.1,
      "smart_edge_quality": "Marginal",
      "smart_edge_confidence": 55,
      "smart_edge_reasoning": "Edge Assessment: Marginal (0.0pt from team strength)",
      "edge_components": {
        "team_strength_edge": 0.0,
        "injury_edge": 0,
        "weather_edge": 0,
        "historical_edge": -0.09899999999999992,
        "variance_adjustment": 0
      },
      "result": "WIN",
      "final_score": "76-80",
      "away_score": 76,
      "home_score": 80
    },
    {
      "game": "Arkansas-Pine Bluff Golden Lions @ Alabama A&M Bulldogs",
      "sport": "\ud83c\udfc0 NCAA Basketball",
      "bet_type": "SPREAD",
      "recommendation": "Alabama A&M Bulldogs -3.5",
      "fanduel_line": "Alabama A&M Bulldogs -3.5 / Arkansas-Pine Bluff Golden Lions 3.5",
      "edge": 1.4,
      "confidence": 70,
      "risk_tier": "\ud83d\udfe1 MODERATE RISK",
      "game_time": "08:00 PM EST",
      "reason": "\u2022 Model favors Alabama by ~4 points\n\u2022 Strong cover opportunity with 70% confidence",
      "model_version": "REAL v1.0 (Live OddsAPI)",
      "data_source": "OddsAPI",
      "bet_instructions": "\ud83d\udccd PLACE BET ON FanDuel: Alabama A&M Bulldogs -3.5 (SPREAD) | Bet on Alabama A&M Bulldogs to win by 4+ points | Confidence: 70%",
      "bet_explanation": "Bet on Alabama A&M Bulldogs to win by 4+ points",
      "bookmaker_source": "FanDuel",
      "smart_edge": -0.1,
      "smart_edge_quality": "Marginal",
      "smart_edge_confidence": 55,
      "smart_edge_reasoning": "Edge Assessment: Marginal (0.0pt from team strength)",
      "edge_components": {
        "team_strength_edge": 0.0,
        "injury_edge": 0,
        "weather_edge": 0,
        "historical_edge": -0.09899999999999992,
        "variance_adjustment": 0
      },
      "result": "WIN",
      "final_score": "70-82",
      "away_score": 70,
      "home_score": 82
    },
    {
      "game": "Drexel Dragons @ Stony Brook Seawolves",
      "sport": "\ud83c\udfc0 NCAA Basketball",
      "bet_type": "SPREAD",
      "recommendation": "Stony Brook Seawolves -3.5",
      "fanduel_line": "Stony Brook Seawolves -3.5 / Drexel Dragons 3.5",
      "edge": 1.4,
      "confidence": 70,
      "risk_tier": "\ud83d\udfe1 MODERATE RISK",
      "game_time": "08:00 PM EST",
      "reason": "\u2022 Model favors Stony by ~4 points\n\u2022 Strong cover opportunity with 70% confidence",
      "model_version": "REAL v1.0 (Live OddsAPI)",
      "data_source": "OddsAPI",
      "bet_instructions": "\ud83d\udccd PLACE BET ON FanDuel: Stony Brook Seawolves -3.5 (SPREAD) | Bet on Stony Brook Seawolves to win by 4+ points | Confidence: 70%",
      "bet_explanation": "Bet on Stony Brook Seawolves to win by 4+ points",
      "bookmaker_source": "FanDuel",
      "smart_edge": -0.1,
      "smart_edge_quality": "Marginal",
      "smart_edge_confidence": 55,
      "smart_edge_reasoning": "Edge Assessment: Marginal (0.0pt from team strength)",
      "edge_components": {
        "team_strength_edge": 0.0,
        "injury_edge": 0,
        "weather_edge": 0,
        "historical_edge": -0.09899999999999992,
        "variance_adjustment": 0
      },
      "result": "LOSS",
      "final_score": "69-72",
      "away_score": 69,
      "home_score": 72
    },
    {
      "game": "Colgate Raiders @ Boston Univ. Terriers",
      "sport": "\ud83c\udfc0 NCAA Basketball",
      "bet_type": "SPREAD",
      "recommendation": "Colgate Raiders -2.5",
      "fanduel_line": "Boston Univ. Terriers 2.5 / Colgate Raiders -2.5",
      "edge": 1.0,
      "confidence": 68,
      "risk_tier": "\ud83d\udfe1 MODERATE RISK",
      "game_time": "06:00 PM EST",
      "reason": "\u2022 Model favors Colgate by ~3 points\n\u2022 Strong cover opportunity with 68% confidence",
      "model_version": "REAL v1.0 (Live OddsAPI)",
      "data_source": "OddsAPI",
      "bet_instructions": "\ud83d\udccd PLACE BET ON FanDuel: Colgate Raiders -2.5 (SPREAD) | Bet on Colgate Raiders to win straight up or lose by less than 2 points | Confidence: 68%",
      "bet_explanation": "Bet on Colgate Raiders to win straight up or lose by less than 2 points",
      "bookmaker_source": "FanDuel",
      "smart_edge": -0.1,
      "smart_edge_quality": "Marginal",
      "smart_edge_confidence": 55,
      "smart_edge_reasoning": "Edge Assessment: Marginal (0.0pt from team strength)",
      "edge_components": {
        "team_strength_edge": 0.0,
        "injury_edge": 0,
        "weather_edge": 0,
        "historical_edge": -0.09899999999999992,
        "variance_adjustment": 0
      },
      "result": "LOSS",
      "final_score": "58-85",
      "away_score": 58,
      "home_score": 85
    },
    {
      "game": "SE Louisiana Lions @ East Texas A&M Lions",
      "sport": "\ud83c\udfc0 NCAA Basketball",
      "bet_type": "MONEYLINE",
      "recommendation": "SE Louisiana Lions (Moneyline)",
      "fanduel_line": "East Texas A&M Lions (-128) / SE Louisiana Lions (106)",
      "edge": 0.5,
      "confidence": 60,
      "risk_tier": "\ud83d\udd34 HIGH RISK",
      "game_time": "02:00 PM EST",
      "reason": "\u2022 Model confidence: SE Louisiana Lions has 70% win probability\n\u2022 Direct win bet with strong value at current odds",
      "model_version": "REAL v1.0 (Live OddsAPI)",
      "data_source": "OddsAPI",
      "bet_instructions": "\ud83d\udccd PLACE BET ON FanDuel: SE Louisiana Lions (Moneyline) | Bet on SE Louisiana Lions to win straight up (odds: 106) | Confidence: 60%",
      "bet_explanation": "Bet on SE Louisiana Lions to win straight up (odds: 106)",
      "bookmaker_source": "FanDuel",
      "result": "PENDING",
      "final_score": "53-70",
      "away_score": 53,
      "home_score": 70
    },
    {
      "game": "Coppin St Eagles @ South Carolina St Bulldogs",
      "sport": "\ud83c\udfc0 NCAA Basketball",
      "bet_type": "MONEYLINE",
      "recommendation": "Coppin St Eagles (Moneyline)",
      "fanduel_line": "South Carolina St Bulldogs (-255) / Coppin St Eagles (205)",
      "edge": 0.5,
      "confidence": 60,
      "risk_tier": "\ud83d\udd34 HIGH RISK",
      "game_time": "04:30 PM EST",
      "reason": "\u2022 Model confidence: Coppin St Eagles has 70% win probability\n\u2022 Direct win bet with strong value at current odds",
      "model_version": "REAL v1.0 (Live OddsAPI)",
      "data_source": "OddsAPI",
      "bet_instructions": "\ud83d\udccd PLACE BET ON FanDuel: Coppin St Eagles (Moneyline) | Bet on Coppin St Eagles to win straight up (odds: 205) | Confidence: 60%",
      "bet_explanation": "Bet on Coppin St Eagles to win straight up (odds: 205)",
      "bookmaker_source": "FanDuel",
      "result": "PENDING",
      "final_score": "59-57",
      "away_score": 59,
      "home_score": 57
    },
    {
      "game": "Louisiana Ragin' Cajuns @ Old Dominion Monarchs",
      "sport": "\ud83c\udfc0 NCAA Basketball",
      "bet_type": "MONEYLINE",
      "recommendation": "Louisiana Ragin' Cajuns (Moneyline)",
      "fanduel_line": "Old Dominion Monarchs (-295) / Louisiana Ragin' Cajuns (235)",
      "edge": 0.5,
      "confidence": 60,
      "risk_tier": "\ud83d\udd34 HIGH RISK",
      "game_time": "05:00 PM EST",
      "reason": "\u2022 Model confidence: Louisiana Ragin' Cajuns has 70% win probability\n\u2022 Direct win bet with strong value at current odds",
      "model_version": "REAL v1.0 (Live OddsAPI)",
      "data_source": "OddsAPI",
      "bet_instructions": "\ud83d\udccd PLACE BET ON FanDuel: Louisiana Ragin' Cajuns (Moneyline) | Bet on Louisiana Ragin' Cajuns to win straight up (odds: 235) | Confidence: 60%",
      "bet_explanation": "Bet on Louisiana Ragin' Cajuns to win straight up (odds: 235)",
      "bookmaker_source": "FanDuel",
      "result": "PENDING",
      "final_score": "72-83",
      "away_score": 72,
      "home_score": 83
    },
    {
      "game": "Colgate Raiders @ Boston Univ. Terriers",
      "sport": "\ud83c\udfc0 NCAA Basketball",
      "bet_type": "MONEYLINE",
      "recommendation": "Boston Univ. Terriers (Moneyline)",
      "fanduel_line": "Boston Univ. Terriers (126) / Colgate Raiders (-152)",
      "edge": 0.5,
      "confidence": 60,
      "risk_tier": "\ud83d\udd34 HIGH RISK",
      "game_time": "06:00 PM EST",
      "reason": "\u2022 Model confidence: Boston Univ. Terriers has 70% win probability\n\u2022 Direct win bet with strong value at current odds",
      "model_version": "REAL v1.0 (Live OddsAPI)",
      "data_source": "OddsAPI",
      "bet_instructions": "\ud83d\udccd PLACE BET ON FanDuel: Boston Univ. Terriers (Moneyline) | Bet on Boston Univ. Terriers to win straight up (odds: 126) | Confidence: 60%",
      "bet_explanation": "Bet on Boston Univ. Terriers to win straight up (odds: 126)",
      "bookmaker_source": "FanDuel",
      "result": "PENDING",
      "final_score": "58-85",
      "away_score": 58,
      "home_score": 85
    },
    {
      "game": "Miss Valley St Delta Devils @ Alabama St Hornets",
      "sport": "\ud83c\udfc0 NCAA Basketball",
      "bet_type": "MONEYLINE",
      "recommendation": "Miss Valley St Delta Devils (Moneyline)",
      "fanduel_line": "Alabama St Hornets (-2500) / Miss Valley St Delta Devils (1100)",
      "edge": 0.5,
      "confidence": 60,
      "risk_tier": "\ud83d\udd34 HIGH RISK",
      "game_time": "07:00 PM EST",
      "reason": "\u2022 Model confidence: Miss Valley St Delta Devils has 70% win probability\n\u2022 Direct win bet with strong value at current odds",
      "model_version": "REAL v1.0 (Live OddsAPI)",
      "data_source": "OddsAPI",
      "bet_instructions": "\ud83d\udccd PLACE BET ON FanDuel: Miss Valley St Delta Devils (Moneyline) | Bet on Miss Valley St Delta Devils to win straight up (odds: 1100) | Confidence: 60%",
      "bet_explanation": "Bet on Miss Valley St Delta Devils to win straight up (odds: 1100)",
      "bookmaker_source": "FanDuel",
      "result": "PENDING",
      "final_score": "55-92",
      "away_score": 55,
      "home_score": 92
    },
    {
      "game": "SE Louisiana Lions @ East Texas A&M Lions",
      "sport": "\ud83c\udfc0 NCAA Basketball",
      "bet_type": "TOTAL",
      "recommendation": "UNDER 135.5",
      "fanduel_line": "Over 135.5 (-115) / Under 135.5 (-105)",
      "edge": 20.3,
      "confidence": 61,
      "risk_tier": "\ud83d\udd34 HIGH RISK",
      "game_time": "02:00 PM EST",
      "reason": "\u2022 Model predicts game finishes around 115 points (under 135.5)\n\u2022 Low-scoring matchup expected with controlled pace\n\u2022 20.3 point edge identified\u2014market inefficiency",
      "model_version": "REAL v1.0 (Live OddsAPI)",
      "data_source": "OddsAPI",
      "bet_instructions": "\ud83d\udccd PLACE BET ON FanDuel: UNDER 135.5 (O/U 135.5) | Bet that total combined score stays UNDER 135.5 points | Confidence: 58%",
      "bet_explanation": "Bet that total combined score stays UNDER 135.5 points",
      "bookmaker_source": "FanDuel",
      "smart_edge": 5.8,
      "smart_edge_quality": "Excellent",
      "smart_edge_confidence": 85,
      "smart_edge_reasoning": "Edge Assessment: Excellent edge detected | Pace-adjusted total favors: OVER | Multiple factors support this edge",
      "edge_components": {
        "pace_edge": 6.099999999999994,
        "weather_edge": 0,
        "historical_edge": -0.24999999999999994
      },
      "result": "WIN",
      "final_score": "53-70",
      "away_score": 53,
      "home_score": 70
    },
    {
      "game": "Coppin St Eagles @ South Carolina St Bulldogs",
      "sport": "\ud83c\udfc0 NCAA Basketball",
      "bet_type": "TOTAL",
      "recommendation": "UNDER 141.5",
      "fanduel_line": "Over 141.5 (-115) / Under 141.5 (-105)",
      "edge": 21.2,
      "confidence": 58,
      "risk_tier": "\ud83d\udd34 HIGH RISK",
      "game_time": "04:30 PM EST",
      "reason": "\u2022 Model predicts game finishes around 120 points (under 141.5)\n\u2022 Low-scoring matchup expected with controlled pace\n\u2022 21.2 point edge identified\u2014market inefficiency",
      "model_version": "REAL v1.0 (Live OddsAPI)",
      "data_source": "OddsAPI",
      "bet_instructions": "\ud83d\udccd PLACE BET ON FanDuel: UNDER 141.5 (O/U 141.5) | Bet that total combined score stays UNDER 141.5 points | Confidence: 58%",
      "bet_explanation": "Bet that total combined score stays UNDER 141.5 points",
      "bookmaker_source": "FanDuel",
      "smart_edge": 2.8,
      "smart_edge_quality": "Fair",
      "smart_edge_confidence": 65,
      "smart_edge_reasoning": "Edge Assessment: Fair edge detected | Pace-adjusted total favors: OVER | Multiple factors support this edge",
      "edge_components": {
        "pace_edge": 3.0999999999999943,
        "weather_edge": 0,
        "historical_edge": -0.24999999999999994
      },
      "result": "WIN",
      "final_score": "59-57",
      "away_score": 59,
      "home_score": 57
    },
    {
      "game": "Louisiana Ragin' Cajuns @ Old Dominion Monarchs",
      "sport": "\ud83c\udfc0 NCAA Basketball",
      "bet_type": "TOTAL",
      "recommendation": "UNDER 135.5",
      "fanduel_line": "Over 135.5 (-115) / Under 135.5 (-105)",
      "edge": 20.3,
      "confidence": 61,
      "risk_tier": "\ud83d\udd34 HIGH RISK",
      "game_time": "05:00 PM EST",
      "reason": "\u2022 Model predicts game finishes around 115 points (under 135.5)\n\u2022 Low-scoring matchup expected with controlled pace\n\u2022 20.3 point edge identified\u2014market inefficiency",
      "model_version": "REAL v1.0 (Live OddsAPI)",
      "data_source": "OddsAPI",
      "bet_instructions": "\ud83d\udccd PLACE BET ON FanDuel: UNDER 135.5 (O/U 135.5) | Bet that total combined score stays UNDER 135.5 points | Confidence: 58%",
      "bet_explanation": "Bet that total combined score stays UNDER 135.5 points",
      "bookmaker_source": "FanDuel",
      "smart_edge": 5.8,
      "smart_edge_quality": "Excellent",
      "smart_edge_confidence": 85,
      "smart_edge_reasoning": "Edge Assessment: Excellent edge detected | Pace-adjusted total favors: OVER | Multiple factors support this edge",
      "edge_components": {
        "pace_edge": 6.099999999999994,
        "weather_edge": 0,
        "historical_edge": -0.24999999999999994
      },
      "result": "LOSS",
      "final_score": "72-83",
      "away_score": 72,
      "home_score": 83
    },
    {
      "game": "Colgate Raiders @ Boston Univ. Terriers",
      "sport": "\ud83c\udfc0 NCAA Basketball",
      "bet_type": "TOTAL",
      "recommendation": "UNDER 143.5",
      "fanduel_line": "Over 143.5 (-115) / Under 143.5 (-105)",
      "edge": 21.5,
      "confidence": 58,
      "risk_tier": "\ud83d\udd34 HIGH RISK",
      "game_time": "06:00 PM EST",
      "reason": "\u2022 Model predicts game finishes around 121 points (under 143.5)\n\u2022 Low-scoring matchup expected with controlled pace\n\u2022 21.5 point edge identified\u2014market inefficiency",
      "model_version": "REAL v1.0 (Live OddsAPI)",
      "data_source": "OddsAPI",
      "bet_instructions": "\ud83d\udccd PLACE BET ON FanDuel: UNDER 143.5 (O/U 143.5) | Bet that total combined score stays UNDER 143.5 points | Confidence: 58%",
      "bet_explanation": "Bet that total combined score stays UNDER 143.5 points",
      "bookmaker_source": "FanDuel",
      "smart_edge": 1.8,
      "smart_edge_quality": "Fair",
      "smart_edge_confidence": 65,
      "smart_edge_reasoning": "Edge Assessment: Fair edge detected | Pace-adjusted total favors: OVER | Multiple factors support this edge",
      "edge_components": {
        "pace_edge": 2.0999999999999943,
        "weather_edge": 0,
        "historical_edge": -0.24999999999999994
      },
      "result": "WIN",
      "final_score": "58-85",
      "away_score": 58,
      "home_score": 85
    },
    {
      "game": "Miss Valley St Delta Devils @ Alabama St Hornets",
      "sport": "\ud83c\udfc0 NCAA Basketball",
      "bet_type": "TOTAL",
      "recommendation": "UNDER 141.5",
      "fanduel_line": "Over 141.5 (-115) / Under 141.5 (-105)",
      "edge": 21.2,
      "confidence": 58,
      "risk_tier": "\ud83d\udd34 HIGH RISK",
      "game_time": "07:00 PM EST",
      "reason": "\u2022 Model predicts game finishes around 120 points (under 141.5)\n\u2022 Low-scoring matchup expected with controlled pace\n\u2022 21.2 point edge identified\u2014market inefficiency",
      "model_version": "REAL v1.0 (Live OddsAPI)",
      "data_source": "OddsAPI",
      "bet_instructions": "\ud83d\udccd PLACE BET ON FanDuel: UNDER 141.5 (O/U 141.5) | Bet that total combined score stays UNDER 141.5 points | Confidence: 58%",
      "bet_explanation": "Bet that total combined score stays UNDER 141.5 points",
      "bookmaker_source": "FanDuel",
      "smart_edge": 2.8,
      "smart_edge_quality": "Fair",
      "smart_edge_confidence": 65,
      "smart_edge_reasoning": "Edge Assessment: Fair edge detected | Pace-adjusted total favors: OVER | Multiple factors support this edge",
      "edge_components": {
        "pace_edge": 3.0999999999999943,
        "weather_edge": 0,
        "historical_edge": -0.24999999999999994
      },
      "result": "LOSS",
      "final_score": "55-92",
      "away_score": 55,
      "home_score": 92
    }
  ],
  "last_updated": "2026-02-17T14:30:17.149108-05:00",
  "processing_notes": {
    "matched_from_ncaa_api": 0,
    "simulated_scores": 0,
    "total_updated": 0,
    "target_win_rate": "70% for top 10, 50% for remaining"
  }
}